{
    "action_delete": "Törlés",
    "actions": "Feladatok",
    "add_item": "Hozzáadás {subject}",
    "browse_file": "tallózás",
    "cancel": "Kilépés",
    "clear_cache": "Gyorsítótár törlése",
    "clear_filtering": "Szűrők tiltása",
    "clone": "Klónozás",
    "close_modal": "Bezárás",
    "close_modal_on_save": "Ablak bezárása mentéskor",
    "columns": "Oszlopok",
    "columns_fit": "Oszlopok elrejtése illesztéshez",
    "confirm_delete": "Biztosan törölni szeretné ezt a bejegyzést?",
    "confirm_delete_multiple": "Biztosan törölni szeretné ezeket a(z) {items_amount} elemet?",
    "edit": "Szerkesztés",
    "edit_item": "Szerkesztés {subject}",
    "enter_x_or_more_characters": "Kérem, adjon meg {remaining_chars} vagy több karaktert",
    "error_generic_title": "Valami hiba történt!",
    "export_to_file": "Exportálás",
    "filtering_add_more": "Több hozzáadása",
    "filtering_and_statement": "ÉS",
    "filtering_cancel": "Mégse",
    "filtering_contains": "tartalmazza",
    "filtering_does_not_have": "nem tartalmazza",
    "filtering_ends_with": "végződik",
    "filtering_equals": "egyenlő",
    "filtering_filter_plural": "Szűrők",
    "filtering_filter_single": "Szűrő",
    "filtering_filter_text": "Szűrő",
    "filtering_greater_than": "nagyobb mint",
    "filtering_greater_than_or_equal": "nagyobb vagy egyenlő",
    "filtering_has": "van",
    "filtering_is_empty": "üres",
    "filtering_is_not_empty": "nem üres",
    "filtering_less_than": "kisebb mint",
    "filtering_less_than_or_equal": "kisebb vagy egyenlő",
    "filtering_not_equals": "nem egyenlő",
    "filtering_operator": "Operátor",
    "filtering_or_statement": "VAGY",
    "filtering_remove_filter": "Szűrő eltávolítása",
    "filtering_remove_filters": "Szűrők eltávolítása",
    "filtering_starts_with": "kezdődik",
    "filtering_text": "Szűrés",
    "loading": "Betöltés...",
    "modal_save": "Mentés",
    "more": "Több",
    "paging_displaying": "{start} elem a(z) {end}-ből . Összesesen {results} elem",
    "paging_filtered_from": "(Kiválasztva összesen {total_results} elemből)",
    "paging_show_entries": "{paging} db mutatása",
    "preview_as_html": "Előnézet HTML-ként",
    "preview_as_plain_text": "Előnézet egyszerű szövegként",
    "print": "Nyomtatás",
    "quick_search": "Gyors keresés",
    "refresh": "Frissítés",
    "reset_ordering": "Rendezés visszaállítása",
    "select_an_option": "Válasszon egy lehetőséget",
    "select_some_options": "Válasszon néhány lehetőséget",
    "settings": "Beállítások",
    "subject": "Elem",
    "subject_plural": "Elemek",
    "time_hour_text": "Óra",
    "time_minute_text": "Perc",
    "time_second_text": "Másodperc",
    "time_text": "Idő",
    "upload_attach_file": "Húzza ide a fájlokat a csatoláshoz, vagy {browse_file}",
    "view": "Megtekintés",
    "view_item": "Megtekintés {subject}"
}